[
  {
    "t": 1771516831,
    "p": 0.0065
  },
  {
    "t": 1771520448,
    "p": 0.0065
  },
  {
    "t": 1771524049,
    "p": 0.0065
  },
  {
    "t": 1771527629,
    "p": 0.0065
  },
  {
    "t": 1771531229,
    "p": 0.0065
  },
  {
    "t": 1771534848,
    "p": 0.0065
  },
  {
    "t": 1771538430,
    "p": 0.006
  },
  {
    "t": 1771542029,
    "p": 0.006
  },
  {
    "t": 1771545651,
    "p": 0.006
  },
  {
    "t": 1771549235,
    "p": 0.0065
  },
  {
    "t": 1771552823,
    "p": 0.0065
  },
  {
    "t": 1771556450,
    "p": 0.0065
  },
  {
    "t": 1771560022,
    "p": 0.0065
  },
  {
    "t": 1771563622,
    "p": 0.0065
  },
  {
    "t": 1771567241,
    "p": 0.0065
  },
  {
    "t": 1771570823,
    "p": 0.0065
  },
  {
    "t": 1771574424,
    "p": 0.0055
  },
  {
    "t": 1771578035,
    "p": 0.0055
  },
  {
    "t": 1771581623,
    "p": 0.013
  },
  {
    "t": 1771585224,
    "p": 0.0115
  },
  {
    "t": 1771588832,
    "p": 0.007
  },
  {
    "t": 1771592449,
    "p": 0.0095
  },
  {
    "t": 1771596022,
    "p": 0.007
  },
  {
    "t": 1771599630,
    "p": 0.0085
  },
  {
    "t": 1771603253,
    "p": 0.0055
  },
  {
    "t": 1771606846,
    "p": 0.008
  },
  {
    "t": 1771610430,
    "p": 0.0075
  },
  {
    "t": 1771614031,
    "p": 0.007
  },
  {
    "t": 1771617626,
    "p": 0.007
  },
  {
    "t": 1771621230,
    "p": 0.007
  },
  {
    "t": 1771624825,
    "p": 0.009
  },
  {
    "t": 1771628425,
    "p": 0.0085
  },
  {
    "t": 1771632034,
    "p": 0.0085
  },
  {
    "t": 1771635630,
    "p": 0.008
  },
  {
    "t": 1771639224,
    "p": 0.008
  },
  {
    "t": 1771642832,
    "p": 0.008
  },
  {
    "t": 1771646432,
    "p": 0.008
  },
  {
    "t": 1771650024,
    "p": 0.008
  },
  {
    "t": 1771653656,
    "p": 0.008
  },
  {
    "t": 1771657227,
    "p": 0.008
  },
  {
    "t": 1771660826,
    "p": 0.008
  },
  {
    "t": 1771664432,
    "p": 0.008
  },
  {
    "t": 1771668027,
    "p": 0.0075
  },
  {
    "t": 1771671635,
    "p": 0.0075
  },
  {
    "t": 1771675235,
    "p": 0.0075
  },
  {
    "t": 1771678834,
    "p": 0.0085
  },
  {
    "t": 1771682426,
    "p": 0.0085
  },
  {
    "t": 1771686034,
    "p": 0.0085
  },
  {
    "t": 1771689626,
    "p": 0.0085
  },
  {
    "t": 1771693241,
    "p": 0.0085
  },
  {
    "t": 1771696832,
    "p": 0.0085
  },
  {
    "t": 1771700433,
    "p": 0.0085
  },
  {
    "t": 1771704034,
    "p": 0.0085
  },
  {
    "t": 1771707634,
    "p": 0.0085
  },
  {
    "t": 1771711227,
    "p": 0.0095
  },
  {
    "t": 1771714828,
    "p": 0.0095
  },
  {
    "t": 1771718435,
    "p": 0.0095
  },
  {
    "t": 1771722027,
    "p": 0.0095
  },
  {
    "t": 1771725628,
    "p": 0.011
  },
  {
    "t": 1771729247,
    "p": 0.0095
  },
  {
    "t": 1771732825,
    "p": 0.0095
  },
  {
    "t": 1771736425,
    "p": 0.0095
  },
  {
    "t": 1771740031,
    "p": 0.0095
  },
  {
    "t": 1771743654,
    "p": 0.0095
  },
  {
    "t": 1771747232,
    "p": 0.0095
  },
  {
    "t": 1771750833,
    "p": 0.0095
  },
  {
    "t": 1771754428,
    "p": 0.0095
  },
  {
    "t": 1771758027,
    "p": 0.0085
  },
  {
    "t": 1771761643,
    "p": 0.0085
  },
  {
    "t": 1771765226,
    "p": 0.0085
  },
  {
    "t": 1771768855,
    "p": 0.0085
  },
  {
    "t": 1771772432,
    "p": 0.0085
  },
  {
    "t": 1771776030,
    "p": 0.0085
  },
  {
    "t": 1771779650,
    "p": 0.0085
  },
  {
    "t": 1771783239,
    "p": 0.0085
  },
  {
    "t": 1771786830,
    "p": 0.0085
  },
  {
    "t": 1771790430,
    "p": 0.0085
  },
  {
    "t": 1771794041,
    "p": 0.009
  },
  {
    "t": 1771797628,
    "p": 0.009
  },
  {
    "t": 1771801228,
    "p": 0.009
  },
  {
    "t": 1771804841,
    "p": 0.0085
  },
  {
    "t": 1771812027,
    "p": 0.0085
  },
  {
    "t": 1771815632,
    "p": 0.01
  },
  {
    "t": 1771819230,
    "p": 0.01
  },
  {
    "t": 1771822827,
    "p": 0.0095
  },
  {
    "t": 1771826436,
    "p": 0.009
  },
  {
    "t": 1771830027,
    "p": 0.01
  },
  {
    "t": 1771833641,
    "p": 0.009
  },
  {
    "t": 1771837233,
    "p": 0.0085
  },
  {
    "t": 1771840825,
    "p": 0.008
  },
  {
    "t": 1771844438,
    "p": 0.011
  },
  {
    "t": 1771848047,
    "p": 0.011
  },
  {
    "t": 1771851625,
    "p": 0.0105
  },
  {
    "t": 1771855225,
    "p": 0.0105
  },
  {
    "t": 1771858844,
    "p": 0.0095
  },
  {
    "t": 1771862426,
    "p": 0.0095
  },
  {
    "t": 1771866029,
    "p": 0.0095
  },
  {
    "t": 1771869649,
    "p": 0.0095
  },
  {
    "t": 1771873226,
    "p": 0.0095
  },
  {
    "t": 1771876826,
    "p": 0.0095
  },
  {
    "t": 1771880433,
    "p": 0.0095
  },
  {
    "t": 1771884027,
    "p": 0.0095
  },
  {
    "t": 1771887629,
    "p": 0.0095
  },
  {
    "t": 1771891242,
    "p": 0.0095
  },
  {
    "t": 1771894827,
    "p": 0.0095
  },
  {
    "t": 1771898433,
    "p": 0.0095
  },
  {
    "t": 1771902032,
    "p": 0.0095
  },
  {
    "t": 1771905627,
    "p": 0.0095
  },
  {
    "t": 1771909245,
    "p": 0.0095
  },
  {
    "t": 1771912833,
    "p": 0.0095
  },
  {
    "t": 1771916434,
    "p": 0.0095
  },
  {
    "t": 1771920040,
    "p": 0.0095
  },
  {
    "t": 1771923641,
    "p": 0.0095
  },
  {
    "t": 1771927227,
    "p": 0.01
  },
  {
    "t": 1771930826,
    "p": 0.01
  },
  {
    "t": 1771934455,
    "p": 0.01
  },
  {
    "t": 1771938031,
    "p": 0.01
  },
  {
    "t": 1771941627,
    "p": 0.01
  },
  {
    "t": 1771945235,
    "p": 0.011
  },
  {
    "t": 1771948827,
    "p": 0.01
  },
  {
    "t": 1771952446,
    "p": 0.011
  },
  {
    "t": 1771956036,
    "p": 0.01
  },
  {
    "t": 1771959628,
    "p": 0.0095
  },
  {
    "t": 1771963228,
    "p": 0.0095
  },
  {
    "t": 1771966834,
    "p": 0.0095
  },
  {
    "t": 1771970443,
    "p": 0.0095
  },
  {
    "t": 1771974053,
    "p": 0.0095
  },
  {
    "t": 1771977647,
    "p": 0.0095
  },
  {
    "t": 1771981228,
    "p": 0.0095
  },
  {
    "t": 1771984842,
    "p": 0.0095
  },
  {
    "t": 1771988433,
    "p": 0.0095
  },
  {
    "t": 1771995628,
    "p": 0.011
  },
  {
    "t": 1771999234,
    "p": 0.011
  },
  {
    "t": 1772002828,
    "p": 0.011
  },
  {
    "t": 1772006430,
    "p": 0.0105
  },
  {
    "t": 1772010035,
    "p": 0.01
  },
  {
    "t": 1772013626,
    "p": 0.01
  },
  {
    "t": 1772017228,
    "p": 0.01
  },
  {
    "t": 1772020852,
    "p": 0.01
  },
  {
    "t": 1772024425,
    "p": 0.0095
  },
  {
    "t": 1772028033,
    "p": 0.0095
  },
  {
    "t": 1772031640,
    "p": 0.0095
  },
  {
    "t": 1772035227,
    "p": 0.0095
  },
  {
    "t": 1772038826,
    "p": 0.0095
  },
  {
    "t": 1772042435,
    "p": 0.0075
  },
  {
    "t": 1772046029,
    "p": 0.008
  },
  {
    "t": 1772049643,
    "p": 0.0085
  },
  {
    "t": 1772053236,
    "p": 0.0085
  },
  {
    "t": 1772056829,
    "p": 0.0085
  },
  {
    "t": 1772060430,
    "p": 0.0085
  },
  {
    "t": 1772064042,
    "p": 0.0085
  },
  {
    "t": 1772067628,
    "p": 0.008
  },
  {
    "t": 1772071229,
    "p": 0.0075
  },
  {
    "t": 1772074856,
    "p": 0.0075
  },
  {
    "t": 1772078440,
    "p": 0.008
  },
  {
    "t": 1772082029,
    "p": 0.008
  },
  {
    "t": 1772085636,
    "p": 0.008
  },
  {
    "t": 1772089231,
    "p": 0.008
  },
  {
    "t": 1772092832,
    "p": 0.008
  },
  {
    "t": 1772096450,
    "p": 0.0065
  },
  {
    "t": 1772100029,
    "p": 0.0065
  },
  {
    "t": 1772103627,
    "p": 0.0075
  },
  {
    "t": 1772110830,
    "p": 0.0085
  },
  {
    "t": 1772114433,
    "p": 0.0085
  },
  {
    "t": 1772118042,
    "p": 0.0085
  },
  {
    "t": 1772121648,
    "p": 0.0085
  },
  {
    "t": 1772125236,
    "p": 0.0085
  },
  {
    "t": 1772128853,
    "p": 0.0085
  },
  {
    "t": 1772132434,
    "p": 0.0085
  },
  {
    "t": 1772136034,
    "p": 0.0085
  },
  {
    "t": 1772139639,
    "p": 0.0085
  },
  {
    "t": 1772143232,
    "p": 0.0085
  },
  {
    "t": 1772146832,
    "p": 0.0085
  },
  {
    "t": 1772150448,
    "p": 0.0085
  },
  {
    "t": 1772154032,
    "p": 0.0085
  },
  {
    "t": 1772157632,
    "p": 0.0085
  },
  {
    "t": 1772161239,
    "p": 0.0085
  },
  {
    "t": 1772164832,
    "p": 0.0085
  },
  {
    "t": 1772168447,
    "p": 0.0085
  },
  {
    "t": 1772172039,
    "p": 0.0085
  },
  {
    "t": 1772175632,
    "p": 0.0085
  },
  {
    "t": 1772179236,
    "p": 0.0085
  },
  {
    "t": 1772182845,
    "p": 0.0085
  },
  {
    "t": 1772186433,
    "p": 0.0085
  },
  {
    "t": 1772190035,
    "p": 0.0085
  },
  {
    "t": 1772197235,
    "p": 0.0085
  },
  {
    "t": 1772200832,
    "p": 0.0065
  },
  {
    "t": 1772204443,
    "p": 0.0065
  },
  {
    "t": 1772208045,
    "p": 0.0065
  },
  {
    "t": 1772215247,
    "p": 0.0065
  },
  {
    "t": 1772218834,
    "p": 0.0065
  },
  {
    "t": 1772222434,
    "p": 0.0065
  },
  {
    "t": 1772226042,
    "p": 0.006
  },
  {
    "t": 1772229636,
    "p": 0.0055
  },
  {
    "t": 1772233241,
    "p": 0.0055
  },
  {
    "t": 1772236846,
    "p": 0.0055
  },
  {
    "t": 1772240430,
    "p": 0.0055
  },
  {
    "t": 1772244036,
    "p": 0.0055
  },
  {
    "t": 1772247633,
    "p": 0.0055
  },
  {
    "t": 1772251232,
    "p": 0.0055
  },
  {
    "t": 1772254832,
    "p": 0.0065
  },
  {
    "t": 1772258438,
    "p": 0.007
  },
  {
    "t": 1772262037,
    "p": 0.0005
  },
  {
    "t": 1772265642,
    "p": 0.0005
  },
  {
    "t": 1772272837,
    "p": 0.0005
  },
  {
    "t": 1772276432,
    "p": 0.0005
  }
]