[
  {
    "t": 1738000803,
    "p": 0.67
  },
  {
    "t": 1738004404,
    "p": 0.625
  },
  {
    "t": 1738008004,
    "p": 0.705
  },
  {
    "t": 1738011604,
    "p": 0.77
  },
  {
    "t": 1738015204,
    "p": 0.795
  },
  {
    "t": 1738018804,
    "p": 0.745
  },
  {
    "t": 1738022404,
    "p": 0.705
  },
  {
    "t": 1738026004,
    "p": 0.705
  },
  {
    "t": 1738029605,
    "p": 0.7
  },
  {
    "t": 1738033204,
    "p": 0.655
  },
  {
    "t": 1738036804,
    "p": 0.645
  },
  {
    "t": 1738040404,
    "p": 0.615
  },
  {
    "t": 1738044004,
    "p": 0.735
  },
  {
    "t": 1738047603,
    "p": 0.64
  },
  {
    "t": 1738051203,
    "p": 0.78
  },
  {
    "t": 1738054804,
    "p": 0.765
  },
  {
    "t": 1738058404,
    "p": 0.765
  },
  {
    "t": 1738062004,
    "p": 0.715
  },
  {
    "t": 1738065604,
    "p": 0.72
  },
  {
    "t": 1738069204,
    "p": 0.73
  },
  {
    "t": 1738072803,
    "p": 0.685
  },
  {
    "t": 1738076403,
    "p": 0.69
  },
  {
    "t": 1738080004,
    "p": 0.645
  },
  {
    "t": 1738083604,
    "p": 0.745
  },
  {
    "t": 1738087204,
    "p": 0.72
  },
  {
    "t": 1738090804,
    "p": 0.68
  },
  {
    "t": 1738094404,
    "p": 0.615
  },
  {
    "t": 1738098004,
    "p": 0.655
  },
  {
    "t": 1738101604,
    "p": 0.91
  },
  {
    "t": 1738105204,
    "p": 0.9995
  },
  {
    "t": 1738108804,
    "p": 0.9995
  }
]